LICENSE
README.md
setup.py
src/aws_session_tx.egg-info/PKG-INFO
src/aws_session_tx.egg-info/SOURCES.txt
src/aws_session_tx.egg-info/dependency_links.txt
src/aws_session_tx.egg-info/entry_points.txt
src/aws_session_tx.egg-info/not-zip-safe
src/aws_session_tx.egg-info/requires.txt
src/aws_session_tx.egg-info/top_level.txt
src/cli/__init__.py
src/cli/config.py
src/cli/main.py
src/cli/models.py
src/cli/sessions.py
src/cli/planner/__init__.py
src/cli/planner/graph.py
src/cli/planner/resolve.py
src/cli/planner/drivers/__init__.py
src/cli/planner/drivers/alb.py
src/cli/planner/drivers/base.py
src/cli/planner/drivers/ec2.py
src/cli/planner/drivers/logs.py
src/cli/planner/drivers/s3.py
src/cli/utils/__init__.py
src/cli/utils/aws.py
src/cli/utils/infra.py
src/cli/utils/output.py
src/cli/utils/retry.py
src/cli/utils/rollback.py